langtag/__init__.py
langtag/cachingurl.py
langtag-0.2.dist-info/LICENSE
langtag-0.2.dist-info/METADATA
langtag-0.2.dist-info/WHEEL
langtag-0.2.dist-info/top_level.txt
langtag-0.2.dist-info/RECORD
