Metadata-Version: 2.2
Name: langtag
Version: 0.2
Summary: BCP47 language tags and tag sets
Author-email: WSTech SIL <fonts@sil.org>
License: Copyright (c) 2019 SIL International (htttp://www.sil.org)
Project-URL: Home-Page, https://github.com/silnrsi/langtags
Classifier: Environment :: Console
Classifier: Programming Language :: Python :: 3.8
Classifier: Intended Audience :: Developers
Classifier: License :: OSI Approved :: MIT License
Classifier: Topic :: Software Development :: Internationalization
Requires-Python: >=3.8
License-File: LICENSE
